{
  "curDate": "2022-03-29",
  "curTime": "10:58:22",
  "executeTemplate": "监测患者生命体征、血氧饱和度变化。",
  "msg": "成功",
  "msgcode": "999999",
  "status": "0",
  "taskSetList": [
    {
      "data": {
        "childItemList": [],
        "exeNoteList": [],
        "noteList": [],
        "subItemList": [
          {
            "subItemDesc": "",
            "subItemId": "1||1",
            "subItemName": "11",
            "subItemSortNo": "",
            "subPositionId": "",
            "subWidgetType": "1"
          }
        ]
      },
      "itemId": "1",
      "itemName": "体温(℃)",
      "itemRequired": "",
      "itemUnit": "℃",
      "itemUrl": "",
      "itemValue": "",
      "positionId": "",
      "valueType": "",
      "widgetType": "4"
    },
    {
      "data": {
        "childItemList": [],
        "exeNoteList": [],
        "noteList": [],
        "subItemList": []
      },
      "itemId": "7",
      "itemName": "血氧饱和度(%)",
      "itemRequired": "",
      "itemUnit": "%",
      "itemUrl": "",
      "itemValue": "",
      "positionId": "",
      "valueType": "",
      "widgetType": "4"
    }
  ]
}
